telextron/__init__.py
telextron/t42view.py
telextron/ttiparse.py
telextron/ttiview.py
telextron-0.0.2.dist-info/LICENSE
telextron-0.0.2.dist-info/METADATA
telextron-0.0.2.dist-info/WHEEL
telextron-0.0.2.dist-info/top_level.txt
telextron-0.0.2.dist-info/RECORD
